{
    "CompileStrategy": "fullobj",
    "cycles_program_begin": 44934275178473,
    "PEModules": [],
    "perf": [
        {
            "stat": [
                "main",
                "entry",
                0.011267900466918945,
                0.011793,
                0.017690000000000001,
                200688,
                200688,
                0.0,
                0.0,
                1693730008.9032049,
                44934275361161
            ],
            "sub": [
                {
                    "stat": [
                        "doParsingAndDesignResolution",
                        "entry",
                        0.14111709594726562,
                        0.018012,
                        0.019199999999999998,
                        209640,
                        210440,
                        0.0,
                        0.0,
                        1693730009.0330541,
                        44934690069449
                    ],
                    "sub": []
                },
                {
                    "stat": [
                        "doParsingAndDesignResolution",
                        "exit",
                        0.15009307861328125,
                        0.018012,
                        0.029966,
                        312372,
                        377404,
                        0.0,
                        0.0,
                        1693730009.0420301,
                        44934718754941
                    ],
                    "sub": []
                },
                {
                    "stat": [
                        "doPostDesignResolutionToVir2Vcs",
                        "entry",
                        0.15527987480163574,
                        0.018012,
                        0.035208999999999997,
                        294304,
                        377404,
                        0.0,
                        0.0,
                        1693730009.0472169,
                        44934735393737
                    ],
                    "sub": [
                        {
                            "stat": [
                                "doUptoVir2VcsNoSepCleanup",
                                "entry",
                                0.1568760871887207,
                                0.018012,
                                0.036805999999999998,
                                294496,
                                377404,
                                0.0,
                                0.0,
                                1693730009.0488131,
                                44934740383561
                            ],
                            "sub": []
                        },
                        {
                            "stat": [
                                "doUptoVir2VcsNoSepCleanup",
                                "exit",
                                0.18531990051269531,
                                0.020354000000000001,
                                0.054822000000000003,
                                307892,
                                377404,
                                0.0053689999999999996,
                                0.0022490000000000001,
                                1693730009.0772569,
                                44934831279273
                            ],
                            "sub": []
                        },
                        {
                            "stat": [
                                "doRadify_vir2vcsAll",
                                "entry",
                                0.18536996841430664,
                                0.020354000000000001,
                                0.054873999999999999,
                                307892,
                                377404,
                                0.0053689999999999996,
                                0.0022490000000000001,
                                1693730009.077307,
                                44934831364553
                            ],
                            "sub": []
                        },
                        {
                            "stat": [
                                "doRadify_vir2vcsAll",
                                "exit",
                                0.19547104835510254,
                                0.020354000000000001,
                                0.064965999999999996,
                                307892,
                                377404,
                                0.0053689999999999996,
                                0.0022490000000000001,
                                1693730009.0874081,
                                44934863680041
                            ],
                            "sub": []
                        }
                    ]
                },
                {
                    "stat": [
                        "doPostDesignResolutionToVir2Vcs",
                        "exit",
                        0.19550204277038574,
                        0.020354000000000001,
                        0.064998,
                        307892,
                        377404,
                        0.0053689999999999996,
                        0.0022490000000000001,
                        1693730009.0874391,
                        44934863719817
                    ],
                    "sub": []
                },
                {
                    "stat": [
                        "doGAToPass2",
                        "entry",
                        0.19551205635070801,
                        0.020354000000000001,
                        0.065008999999999997,
                        307892,
                        377404,
                        0.0053689999999999996,
                        0.0022490000000000001,
                        1693730009.0874491,
                        44934863746153
                    ],
                    "sub": [
                        {
                            "stat": [
                                "DoPass2",
                                "entry",
                                0.22231006622314453,
                                0.020354000000000001,
                                0.066230999999999998,
                                295676,
                                377404,
                                0.011204,
                                0.020393000000000001,
                                1693730009.1142471,
                                44934949416457
                            ],
                            "sub": []
                        },
                        {
                            "stat": [
                                "DoPass2",
                                "exit",
                                0.23671603202819824,
                                0.020354000000000001,
                                0.078489000000000003,
                                304236,
                                377404,
                                0.012688,
                                0.020393000000000001,
                                1693730009.128653,
                                44934995402185
                            ],
                            "sub": []
                        }
                    ]
                },
                {
                    "stat": [
                        "doGAToPass2",
                        "exit",
                        0.23890590667724609,
                        0.020354000000000001,
                        0.080680000000000002,
                        304236,
                        377404,
                        0.012688,
                        0.020393000000000001,
                        1693730009.1308429,
                        44935002405001
                    ],
                    "sub": []
                }
            ]
        },
        {
            "stat": [
                "main",
                "exit",
                0.23910188674926758,
                0.020354000000000001,
                0.080876000000000003,
                304236,
                377404,
                0.012688,
                0.020393000000000001,
                1693730009.1310389,
                44935002982057
            ],
            "sub": []
        }
    ],
    "CurCompileUdps": {},
    "PrevCompiledModules": {
        "_vcs_unit__2444631337": {
            "jNxLu_d": {
                "checksum": 0,
                "mode": 4,
                "bytes": 13498,
                "mod": "_vcs_unit__2444631337",
                "archive": "archive.1/_15213_archive_1.a",
                "out": "jNxLu_d.o"
            }
        },
        "std": {
            "reYIK_d": {
                "checksum": 0,
                "mode": 4,
                "bytes": 43168,
                "mod": "std",
                "archive": "archive.1/_prev_archive_1.a",
                "out": "reYIK_d.o"
            }
        },
        "tb": {
            "g7hgQ_d": {
                "checksum": 0,
                "mode": 4,
                "bytes": 19168,
                "mod": "tb",
                "archive": "archive.1/_15213_archive_1.a",
                "out": "g7hgQ_d.o"
            }
        },
        "...MASTER...": {
            "amcQw_d": {
                "checksum": 0,
                "mode": 4,
                "bytes": 8178,
                "mod": "...MASTER...",
                "out": "objs/amcQw_d.o"
            }
        }
    },
    "incremental": "on",
    "SIMBData": {
        "archive": "archive.1/_15213_archive_1.a",
        "text": 0,
        "out": "amcQwB.o",
        "bytes": 116582
    },
    "Misc": {
        "csrc_abs": "/home/stone/System_Verilog_Udemy/3_Ramdomiztion/4_Constraint_Range/csrc",
        "vcs_version": "O-2018.09-SP2_Full64",
        "vcs_build_date": "Build Date = Feb 28 2019 22:34:30",
        "master_pid": 15213,
        "daidir_abs": "/home/stone/System_Verilog_Udemy/3_Ramdomiztion/4_Constraint_Range/simv.daidir",
        "VCS_HOME": "/usr/stone/software/vcs2018/vcs/O-2018.09-SP2",
        "hostname": "",
        "csrc": "csrc",
        "cwd": "/home/stone/System_Verilog_Udemy/3_Ramdomiztion/4_Constraint_Range",
        "archive_dir": "archive.1",
        "daidir": "simv.daidir",
        "default_output_dir": "csrc"
    },
    "MlibObjs": {},
    "NameTable": {
        "std": [
            "std",
            "reYIK",
            "module",
            2
        ],
        "_vcs_unit__2444631337": [
            "_vcs_unit__2444631337",
            "jNxLu",
            "module",
            1
        ],
        "tb": [
            "tb",
            "g7hgQ",
            "module",
            3
        ],
        "...MASTER...": [
            "SIM",
            "amcQw",
            "module",
            4
        ]
    },
    "stat": {
        "realTime": 0.23914408683776855,
        "ru_self_cgstart": {
            "ru_nvcsw": 149,
            "ru_utime_sec": 0.020354000000000001,
            "ru_stime_sec": 0.066279000000000005,
            "ru_maxrss_kb": 113736,
            "ru_minflt": 11373,
            "ru_majflt": 2,
            "ru_nivcsw": 17
        },
        "cpu_cycles_total": 727869312,
        "totalObjSize": 149064,
        "ru_childs_cgstart": {
            "ru_nvcsw": 25,
            "ru_utime_sec": 0.011204,
            "ru_stime_sec": 0.020393000000000001,
            "ru_maxrss_kb": 113736,
            "ru_minflt": 5099,
            "ru_majflt": 0,
            "ru_nivcsw": 0
        },
        "cpu_cycles_cgstart": 44934949479785,
        "nMops": 1423,
        "ru_childs_end": {
            "ru_nvcsw": 26,
            "ru_utime_sec": 0.012688,
            "ru_stime_sec": 0.020393000000000001,
            "ru_maxrss_kb": 113736,
            "ru_minflt": 5342,
            "ru_majflt": 0,
            "ru_nivcsw": 0
        },
        "nQuads": 572,
        "CodeGen(%)": 4.4912535560801379,
        "Frontend(%)": 95.508746443919861,
        "outputSizePerQuad": 260.60139860139861,
        "ru_self_end": {
            "ru_nvcsw": 151,
            "ru_utime_sec": 0.020354000000000001,
            "ru_stime_sec": 0.080904000000000004,
            "ru_maxrss_kb": 121008,
            "ru_minflt": 12802,
            "ru_majflt": 3,
            "ru_nivcsw": 27
        },
        "cpu_cycles_end": 44935003047785,
        "peak_mem_kb": 377404
    },
    "cpu_cycles_pass2_start": 44934949427785,
    "LVLData": [
        "SIM"
    ],
    "CurCompileModules": [
        "...MASTER...",
        "_vcs_unit__2444631337",
        "_vcs_unit__2444631337",
        "std",
        "tb",
        "tb"
    ],
    "CompileProcesses": [
        "cgproc.15213.json"
    ],
    "rlimit": {
        "data": -1,
        "stack": -1
    },
    "CompileStatus": "Successful"
}